[
    {
        "timestamp": "2025-09-01 10:14:16",
        "dataset": "facebook_combined.txt",
        "approach": "baseline",
        "algorithm": "CELFPP",
        "community_alg": null,
        "runtime": 84.352729,
        "k": 50,
        "modularity": 0.0,
        "spread_initial": 1,
        "spread_final": 416,
        "budget_per_community": null,
        "seeds_initial": [
            2331
        ],
        "seeds_final": [
            2331,
            107,
            1714,
            2151,
            2000,
            2839,
            484,
            3042,
            3667,
            2214,
            207,
            2309,
            2093,
            176,
            2420,
            2104,
            2329,
            2201,
            1280,
            1289,
            1644,
            1628,
            3922,
            2430,
            185,
            2188,
            2985,
            1949,
            2100,
            1868,
            2621,
            3695,
            2287,
            3109,
            1689,
            3384,
            3929,
            1929,
            2803,
            3152,
            2579,
            2449,
            787,
            2407,
            2069,
            3120,
            3831,
            579,
            2347,
            1619
        ]
    },
    {
        "timestamp": "2025-09-01 10:14:18",
        "dataset": "facebook_combined.txt",
        "approach": "community-aware",
        "algorithm": "CELFPP",
        "community_alg": "Louvain",
        "runtime": 1.698184,
        "k": 50,
        "modularity": 0.834944,
        "spread_initial": 296,
        "spread_final": 35,
        "budget_per_community": null,
        "seeds_initial": [
            0,
            348,
            107,
            136
        ],
        "seeds_final": [
            0,
            188,
            322,
            98,
            348,
            366,
            395,
            426,
            399,
            107,
            136
        ]
    },
    [
        {
            "timestamp": "2025-09-01 10:28:15",
            "dataset": "facebook_combined.txt",
            "approach": "baseline",
            "algorithm": "CELFPP",
            "community_alg": null,
            "runtime": 81.733192,
            "k": 50,
            "modularity": 0.0,
            "spread_initial": 1,
            "spread_final": 416,
            "budget_per_community": null,
            "seeds_initial": [
                2331
            ],
            "seeds_final": [
                2331,
                107,
                1714,
                2151,
                2000,
                2839,
                484,
                3042,
                3667,
                2214,
                207,
                2309,
                2093,
                176,
                2420,
                2104,
                2329,
                2201,
                1280,
                1289,
                1644,
                1628,
                3922,
                2430,
                185,
                2188,
                2985,
                1949,
                2100,
                1868,
                2621,
                3695,
                2287,
                3109,
                1689,
                3384,
                3929,
                1929,
                2803,
                3152,
                2579,
                2449,
                787,
                2407,
                2069,
                3120,
                3831,
                579,
                2347,
                1619
            ]
        },
        {
            "timestamp": "2025-09-01 10:28:17",
            "dataset": "facebook_combined.txt",
            "approach": "community-aware",
            "algorithm": "CELFPP",
            "community_alg": "Louvain",
            "runtime": 1.435731,
            "k": 50,
            "modularity": 0.834871,
            "spread_initial": 213,
            "spread_final": 56,
            "budget_per_community": null,
            "seeds_initial": [
                0,
                348,
                107,
                136
            ],
            "seeds_final": [
                0,
                252,
                315,
                65,
                348,
                376,
                370,
                419,
                395,
                107,
                136
            ]
        }
    ],
    [
        {
            "timestamp": "2025-09-01 10:33:00",
            "dataset": "wiki-Vote.txt",
            "approach": "baseline",
            "algorithm": "CELFPP",
            "community_alg": null,
            "runtime": 283.347141,
            "k": 50,
            "modularity": 0.0,
            "spread_initial": 506,
            "spread_final": 608,
            "budget_per_community": null,
            "seeds_initial": [
                1549
            ],
            "seeds_final": [
                1549,
                5479,
                7092,
                4494,
                4920,
                6914,
                2543,
                3472,
                432,
                2353,
                3508,
                4355,
                1971,
                2272,
                3006,
                4866,
                2619,
                3452,
                1065,
                974,
                5011,
                626,
                2290,
                2996,
                5240,
                1799,
                6660,
                6488,
                6432,
                2989,
                1783,
                3443,
                1621,
                3033,
                5829,
                1798,
                2662,
                2181,
                1460,
                1230,
                4667,
                1409,
                6455,
                6993,
                3258,
                1360,
                2764,
                3005,
                3119,
                3380
            ]
        },
        {
            "timestamp": "2025-09-01 10:33:10",
            "dataset": "wiki-Vote.txt",
            "approach": "community-aware",
            "algorithm": "CELFPP",
            "community_alg": "Louvain",
            "runtime": 9.392614,
            "k": 50,
            "modularity": 0.42868,
            "spread_initial": 576,
            "spread_final": 553,
            "budget_per_community": null,
            "seeds_initial": [
                11,
                1166,
                737,
                1133
            ],
            "seeds_final": [
                11,
                922,
                600,
                769,
                1836,
                691,
                1166,
                988,
                825,
                465,
                1042,
                449,
                737,
                1374,
                1098,
                967,
                1074,
                580,
                1133,
                766,
                1542,
                1247,
                1470,
                582
            ]
        }
    ],
    [
        {
            "timestamp": "2025-09-01 13:37:35",
            "dataset": "soc-sign-bitcoinotc.csv",
            "approach": "baseline",
            "algorithm": "CELFPP",
            "community_alg": null,
            "runtime": 13.639027,
            "k": 50,
            "modularity": 0.0,
            "spread_initial": 15,
            "spread_final": 105,
            "budget_per_community": null,
            "seeds_initial": [
                35
            ],
            "seeds_final": [
                35,
                2125,
                905,
                1810,
                1566,
                1585,
                4532,
                4011,
                204,
                5037,
                5207,
                5738,
                792,
                1795,
                550,
                3988,
                4405,
                2315,
                4778,
                1612,
                1656,
                3616,
                3627,
                4682,
                556,
                4360,
                620,
                2570,
                3185,
                3451,
                4197,
                4320,
                1832,
                1646,
                2584,
                2716,
                2877,
                3254,
                2281,
                2516,
                3324,
                4756,
                5441,
                3879,
                5582,
                178,
                3702,
                3872,
                4116,
                4744
            ]
        },
        {
            "timestamp": "2025-09-01 13:37:36",
            "dataset": "soc-sign-bitcoinotc.csv",
            "approach": "community-aware",
            "algorithm": "CELFPP",
            "community_alg": "Louvain",
            "runtime": 1.001941,
            "k": 50,
            "modularity": -0.33498,
            "spread_initial": 31,
            "spread_final": 82,
            "budget_per_community": null,
            "seeds_initial": [
                545,
                1,
                3,
                13,
                17,
                23,
                280,
                35,
                328,
                33
            ],
            "seeds_final": [
                545,
                115,
                62,
                96,
                384,
                1,
                7,
                198,
                309,
                480,
                3,
                13,
                304,
                303,
                490,
                17,
                23,
                280,
                215,
                169,
                451,
                527,
                35,
                371,
                65,
                79,
                248,
                328,
                146,
                33,
                224
            ]
        }
    ],
    [
        {
            "timestamp": "2025-09-01 13:43:22",
            "dataset": "soc-Epinions1.txt",
            "approach": "community-aware",
            "algorithm": "CELFPP",
            "community_alg": "Louvain",
            "runtime": 271.187168,
            "k": 50,
            "modularity": 0.439042,
            "spread_initial": 0,
            "spread_final": 0,
            "budget_per_community": null,
            "seeds_initial": [],
            "seeds_final": []
        }
    ],
    [
        {
            "timestamp": "2025-09-01 13:46:54",
            "dataset": "facebook_combined.txt",
            "approach": "community-aware",
            "algorithm": "CELFPP",
            "community_alg": "Louvain",
            "runtime": 1.321233,
            "k": 50,
            "modularity": 0.83497,
            "spread_initial": 240,
            "spread_final": 138,
            "budget_per_community": null,
            "seeds_initial": [
                0,
                348,
                107,
                136
            ],
            "seeds_final": [
                0,
                56,
                21,
                304,
                348,
                370,
                414,
                376,
                400,
                107,
                136
            ]
        }
    ],
    [
        {
            "timestamp": "2025-09-01 13:49:27",
            "dataset": "soc-Epinions1.txt",
            "approach": "community-aware",
            "algorithm": "PAGERANK",
            "community_alg": "Louvain",
            "runtime": 12.060478,
            "k": 50,
            "modularity": 0.4484,
            "spread_initial": 2227,
            "spread_final": 52,
            "budget_per_community": null,
            "seeds_initial": [
                61954,
                70038,
                63193,
                63369,
                70370,
                64415,
                65972,
                67204,
                67329,
                71755,
                71869,
                71993,
                72164,
                72178,
                72179,
                72446,
                72555,
                72561,
                75414,
                72640,
                72794,
                72802,
                72813,
                75451,
                75453,
                75460,
                75478,
                73234,
                75488,
                75492,
                73417,
                75528,
                73626,
                75556,
                75756,
                75769,
                74457,
                75638,
                74565,
                75648,
                75651,
                74764,
                74780,
                74843,
                71749,
                74906,
                75701,
                74984,
                75040,
                75872
            ],
            "seeds_final": [
                61954,
                70038,
                63193,
                63369,
                70370,
                64415,
                65972,
                67204,
                67329,
                71755,
                71869,
                71993,
                72164,
                72178,
                72179,
                72446,
                72555,
                72561,
                75414,
                72640,
                72794,
                72802,
                72813,
                75451,
                75453,
                75460,
                75478,
                73234,
                75488,
                75492,
                73417,
                75528,
                73626,
                75556,
                75756,
                75769,
                74457,
                75638,
                74565,
                75648,
                75651,
                74764,
                74780,
                74843,
                71749,
                74906,
                75701,
                74984,
                75040,
                75872
            ]
        }
    ],
    [
        {
            "timestamp": "2025-09-01 13:50:05",
            "dataset": "soc-Epinions1.txt",
            "approach": "baseline",
            "algorithm": "PAGERANK",
            "community_alg": null,
            "runtime": 0.661268,
            "k": 50,
            "modularity": 0.0,
            "spread_initial": 2021,
            "spread_final": 2124,
            "budget_per_community": null,
            "seeds_initial": [
                18
            ],
            "seeds_final": [
                18,
                763,
                5232,
                634,
                645,
                143,
                71399,
                4920,
                5227,
                790,
                737,
                44,
                1835,
                136,
                1719,
                3924,
                1179,
                4415,
                7047,
                4416,
                118,
                1621,
                791,
                1753,
                637,
                27,
                1619,
                128,
                1516,
                1720,
                770,
                780,
                1059,
                5224,
                1,
                1440,
                2704,
                40,
                725,
                77,
                4969,
                34,
                28,
                2512,
                1669,
                2239,
                1398,
                849,
                751,
                824
            ]
        },
        {
            "timestamp": "2025-09-01 13:50:16",
            "dataset": "soc-Epinions1.txt",
            "approach": "community-aware",
            "algorithm": "PAGERANK",
            "community_alg": "Louvain",
            "runtime": 11.230317,
            "k": 50,
            "modularity": 0.44771,
            "spread_initial": 2096,
            "spread_final": 53,
            "budget_per_community": null,
            "seeds_initial": [
                60261,
                60440,
                70038,
                63369,
                70370,
                64415,
                71244,
                65972,
                67204,
                71697,
                71755,
                71869,
                71993,
                72164,
                72178,
                75332,
                72446,
                75414,
                72640,
                72794,
                72813,
                72964,
                75451,
                75453,
                73068,
                75478,
                73234,
                75488,
                75492,
                73417,
                75528,
                75556,
                75756,
                75769,
                74457,
                75638,
                74565,
                75648,
                74631,
                75664,
                74676,
                74692,
                74764,
                74780,
                74843,
                71749,
                75701,
                74984,
                75040,
                75872
            ],
            "seeds_final": [
                60261,
                60440,
                70038,
                63369,
                70370,
                64415,
                71244,
                65972,
                67204,
                71697,
                71755,
                71869,
                71993,
                72164,
                72178,
                75332,
                72446,
                75414,
                72640,
                72794,
                72813,
                72964,
                75451,
                75453,
                73068,
                75478,
                73234,
                75488,
                75492,
                73417,
                75528,
                75556,
                75756,
                75769,
                74457,
                75638,
                74565,
                75648,
                74631,
                75664,
                74676,
                74692,
                74764,
                74780,
                74843,
                71749,
                75701,
                74984,
                75040,
                75872
            ]
        }
    ],
    [
        {
            "timestamp": "2025-09-02 05:44:46",
            "dataset": "facebook_combined.txt",
            "approach": "baseline",
            "algorithm": "CELFPP",
            "community_alg": null,
            "runtime": 84.726551,
            "k": 50,
            "modularity": 0.0,
            "spread_initial": 1,
            "spread_final": 416,
            "budget_per_community": null,
            "seeds_initial": [
                2331
            ],
            "seeds_final": [
                2331,
                107,
                1714,
                2151,
                2000,
                2839,
                484,
                3042,
                3667,
                2214,
                207,
                2309,
                2093,
                176,
                2420,
                2104,
                2329,
                2201,
                1280,
                1289,
                1644,
                1628,
                3922,
                2430,
                185,
                2188,
                2985,
                1949,
                2100,
                1868,
                2621,
                3695,
                2287,
                3109,
                1689,
                3384,
                3929,
                1929,
                2803,
                3152,
                2579,
                2449,
                787,
                2407,
                2069,
                3120,
                3831,
                579,
                2347,
                1619
            ]
        },
        {
            "timestamp": "2025-09-02 05:44:48",
            "dataset": "facebook_combined.txt",
            "approach": "community-aware",
            "algorithm": "CELFPP",
            "community_alg": "Louvain",
            "runtime": 1.525517,
            "k": 50,
            "modularity": 0.834965,
            "spread_initial": 175,
            "spread_final": 82,
            "budget_per_community": null,
            "seeds_initial": [
                0,
                348,
                107,
                136
            ],
            "seeds_final": [
                0,
                252,
                315,
                65,
                348,
                353,
                366,
                402,
                397,
                107,
                136
            ]
        }
    ],
    [
        {
            "timestamp": "2025-09-02 10:37:04",
            "dataset": "facebook_combined.txt",
            "approach": "baseline",
            "algorithm": "CELFPP",
            "community_alg": null,
            "runtime": 84.184736,
            "k": 50,
            "modularity": 0.0,
            "spread_initial": 1,
            "spread_final": 416,
            "budget_per_community": null,
            "seeds_initial": [
                2331
            ],
            "seeds_final": [
                2331,
                107,
                1714,
                2151,
                2000,
                2839,
                484,
                3042,
                3667,
                2214,
                207,
                2309,
                2093,
                176,
                2420,
                2104,
                2329,
                2201,
                1280,
                1289,
                1644,
                1628,
                3922,
                2430,
                185,
                2188,
                2985,
                1949,
                2100,
                1868,
                2621,
                3695,
                2287,
                3109,
                1689,
                3384,
                3929,
                1929,
                2803,
                3152,
                2579,
                2449,
                787,
                2407,
                2069,
                3120,
                3831,
                579,
                2347,
                1619
            ]
        },
        {
            "timestamp": "2025-09-02 10:37:06",
            "dataset": "facebook_combined.txt",
            "approach": "community-aware",
            "algorithm": "CELFPP",
            "community_alg": "Louvain",
            "runtime": 1.540304,
            "k": 50,
            "modularity": 0.834941,
            "spread_initial": 130,
            "spread_final": 120,
            "budget_per_community": null,
            "seeds_initial": [
                0,
                348,
                107,
                136
            ],
            "seeds_final": [
                0,
                188,
                322,
                98,
                348,
                373,
                353,
                391,
                403,
                107,
                136
            ]
        }
    ]
]